Workbook

Sheet PRESUPUESTO
B1: Municipio De Rincon De Romos
B2: Presupuesto Anual Para El Ejercicio Fiscal 2026 de Recursos Fiscales
B4: Etapa 1 Planeación: (Proyecto) | C4: Verificación de Fraccionamientos y Condominios, (vivienda para el bienestar, proyecto IVSOP, condominios, Rincón Real, I, II y III, Villas de la Plata, La Arbolada, Allegro Residencial), así como los proyectos de inversión como es la Fábrica de productos lácteos de Pabellón de Hidalgo, el nuevo hospital del ISSSTE, el nuevo centro CECI del IMSS, proyecto de procesamiento de Basura y Residuos Solidos Urbanos, Nueva Universidad Rosario Castellanos, entre otros muchos más.
B7: Etapa 2 Programación: (alcance) | C7: La revisión y análisis en campo de los diferentes trámites administrativos propios de la Dirección (Constancia Municipal de Compatibilidad urbanística, Licencia de Construcción, Subdivisión y fusión de predios, constancia de numero oficial por mencionar algunos traites) que son la base de ingreso de esta área, el cual se superó lo proyectado para este actual ejercicio 2025.
B11: Etapa 3 Presupuestación:
B12: Notas | D12: Proyecto | E12: 067 | F12: PRESUPUESTO | H12: U.A | I12: =+VLOOKUP(E12,CONDICIONES!A4:B4,2,FALSE) -> H001 | J12: EJE | K12: =+VLOOKUP(E12,CONDICIONES!C4:D4,2,FALSE) -> 2
B13: =+VLOOKUP(E12,CONDICIONES!C4:N4,12,FALSE) -> 1 vehículo | D13: =+VLOOKUP(E12,PROYECTO!B:C,2,FALSE) -> CONTROL DEL DESARROLLO URBANO | F13: =+VLOOKUP(E12,CONDICIONES!C4:I4,7,FALSE) -> 700000 | H13: =+VLOOKUP(I12,U.A!B:C,2,FALSE) -> Dirección de Planeación y Desarrollo Urbano | J13: =+VLOOKUP(K12,EJES!B:C,2,FALSE) -> RINCÓN RESPONSABLE Y CULTO
B18: Unidad Administrativa | C18: Concepto de U.A | D18: Proyecto | E18: Concepto de Proyecto | F18: F.F | G18: Concepto de F.F | H18: Objeto de Gasto | I18: Concepto de COG | J18: Tipo de Gasto | K18: Importe
B19: H001 | C19: =+VLOOKUP(B19,[1]U.A!$B$3:$C$50,2,FALSE) -> Dirección de Planeación y Desarrollo Urbano | D19: =+$E$12 -> 067 | E19: =+$D$13 -> CONTROL DEL DESARROLLO URBANO | F19: 1101 | G19: =+VLOOKUP(F19,[1]F.F!$B$3:$C$7,2,FALSE) -> Recursos Fiscales 2026 | H19: 54101 | I19: =+VLOOKUP(H19,[1]COG!$B$3:$C$290,2,FALSE) -> VEHÍCULOS Y EQUIPO TERRESTRE | J19: =+IF(H19<49999,1,2) -> 2 | K19: 370000
B20: H001 | C20: =+VLOOKUP(B20,[1]U.A!$B$3:$C$50,2,FALSE) -> Dirección de Planeación y Desarrollo Urbano | D20: =+$E$12 -> 067 | E20: =+$D$13 -> CONTROL DEL DESARROLLO URBANO | F20: 1101 | G20: =+VLOOKUP(F20,[1]F.F!$B$3:$C$7,2,FALSE) -> Recursos Fiscales 2026 | H20: 29601 | I20: =+VLOOKUP(H20,[1]COG!$B$3:$C$290,2,FALSE) -> REFACCIONES Y ACCESORIOS MENORES DE EQUIPO DE TRANSPORTE | J20: =+IF(H20<49999,1,2) -> 1 | K20: 25000
B21: H001 | C21: =+VLOOKUP(B21,[1]U.A!$B$3:$C$50,2,FALSE) -> Dirección de Planeación y Desarrollo Urbano | D21: =+$E$12 -> 067 | E21: =+$D$13 -> CONTROL DEL DESARROLLO URBANO | F21: 1101 | G21: =+VLOOKUP(F21,[1]F.F!$B$3:$C$7,2,FALSE) -> Recursos Fiscales 2026 | H21: 35501 | I21: =+VLOOKUP(H21,[1]COG!$B$3:$C$290,2,FALSE) -> REPARACIÓN Y MANTENIMIENTO DE EQUIPO DE TRANSPORTE | J21: =+IF(H21<49999,1,2) -> 1 | K21: 25000
B22: H001 | C22: =+VLOOKUP(B22,[1]U.A!$B$3:$C$50,2,FALSE) -> Dirección de Planeación y Desarrollo Urbano | D22: =+$E$12 -> 067 | E22: =+$D$13 -> CONTROL DEL DESARROLLO URBANO | F22: 1101 | G22: =+VLOOKUP(F22,[1]F.F!$B$3:$C$7,2,FALSE) -> Recursos Fiscales 2026 | H22: 26101 | I22: =+VLOOKUP(H22,[1]COG!$B$3:$C$290,2,FALSE) -> COMBUSTIBLES, LUBRICANTES Y ADITIVOS | J22: =+IF(H22<49999,1,2) -> 1 | K22: 50000
B23: H001 | C23: =+VLOOKUP(B23,[1]U.A!$B$3:$C$50,2,FALSE) -> Dirección de Planeación y Desarrollo Urbano | D23: =+$E$12 -> 067 | E23: =+$D$13 -> CONTROL DEL DESARROLLO URBANO | F23: 1101 | G23: =+VLOOKUP(F23,[1]F.F!$B$3:$C$7,2,FALSE) -> Recursos Fiscales 2026 | H23: 51901 | I23: =+VLOOKUP(H23,[1]COG!$B$3:$C$290,2,FALSE) -> OTROS MOBILIARIOS Y EQUIPOS DE ADMINISTRACIÓN | J23: =+IF(H23<49999,1,2) -> 2 | K23: 80000
B24: H001 | C24: =+VLOOKUP(B24,[1]U.A!$B$3:$C$50,2,FALSE) -> Dirección de Planeación y Desarrollo Urbano | D24: =+$E$12 -> 067 | E24: =+$D$13 -> CONTROL DEL DESARROLLO URBANO | F24: 1101 | G24: =+VLOOKUP(F24,[1]F.F!$B$3:$C$7,2,FALSE) -> Recursos Fiscales 2026 | H24: 21101 | I24: =+VLOOKUP(H24,[1]COG!$B$3:$C$290,2,FALSE) -> MATERIALES, ÚTILES Y EQUIPOS MENORES DE OFICINA | J24: =+IF(H24<49999,1,2) -> 1 | K24: 20000
B25: H001 | C25: =+VLOOKUP(B25,[1]U.A!$B$3:$C$50,2,FALSE) -> Dirección de Planeación y Desarrollo Urbano | D25: =+$E$12 -> 067 | E25: =+$D$13 -> CONTROL DEL DESARROLLO URBANO | F25: 1101 | G25: =+VLOOKUP(F25,[1]F.F!$B$3:$C$7,2,FALSE) -> Recursos Fiscales 2026 | H25: 51501 | I25: =+VLOOKUP(H25,[1]COG!$B$3:$C$290,2,FALSE) -> EQUIPO DE CÓMPUTO Y DE TECNOLOGÍAS DE LA INFORMACIÓN | J25: =+IF(H25<49999,1,2) -> 2 | K25: 80000
B26: H001 | C26: =+VLOOKUP(B26,[1]U.A!$B$3:$C$50,2,FALSE) -> Dirección de Planeación y Desarrollo Urbano | D26: =+$E$12 -> 067 | E26: =+$D$13 -> CONTROL DEL DESARROLLO URBANO | F26: 1101 | G26: =+VLOOKUP(F26,[1]F.F!$B$3:$C$7,2,FALSE) -> Recursos Fiscales 2026 | H26: 22102 | I26: =+VLOOKUP(H26,[1]COG!$B$3:$C$290,2,FALSE) -> ALIMENTOS EN OFICINAS Y LUGARES DE TRABAJO | J26: =+IF(H26<49999,1,2) -> 1 | K26: 15000
B27: H001 | C27: =+VLOOKUP(B27,[1]U.A!$B$3:$C$50,2,FALSE) -> Dirección de Planeación y Desarrollo Urbano | D27: =+$E$12 -> 067 | E27: =+$D$13 -> CONTROL DEL DESARROLLO URBANO | F27: 1101 | G27: =+VLOOKUP(F27,[1]F.F!$B$3:$C$7,2,FALSE) -> Recursos Fiscales 2026 | H27: 22103 | I27: =+VLOOKUP(H27,[1]COG!$B$3:$C$290,2,FALSE) -> ALIMENTOS EN EVENTOS OFICIALES | J27: =+IF(H27<49999,1,2) -> 1 | K27: 35000
B29: TOTAL | K29: =SUM(K19:K28) -> 700000
E34: LIC. EN URB. JESÚS BERNARDO DÍAZ DE LEÓN GUTIERREZ
E35: FIRMA Y NOMBRE DEL DIRECTOR
D38: Numero de poblacion a beneficiar | G38: 57369

Sheet U.A
B2: U.A | C2: CONCEPTO
B3: A001 | C3: H Cabildo
B4: B001 | C4: Coordinación de Gestión Social
B5: B002 | C5: Dirección de Comunicación Social y Relaciones Públicas
B6: B003 | C6: Dirección de la Instancia de la Juventud
B7: B004 | C7: Coordinación de Gestión y Proyectos Estrategicos
B8: C001 | C8: Dirección del Sistema para el Desarrollo Integral de la Familia
B9: C002 | C9: Coordinador de la Estancia Infantil (CENDI- DIF)
B10: C003 | C10: Dirección de la Instancia de la Mujer
B11: D001 | C11: Órgano Interno de Control
B12: D002 | C12: Departamento de Transparencia
B13: D003 | C13: Autoridad Investigadora
... B49: N003 | C49: Departamento de Promoción y Concertación Social

Sheet F.F
B2: F.F | C2: CONCEPTO
B3: 1101 | C3: Recursos Fiscales 2026
B4: 1501 | C4: Participaciones Federales 2026
B5: 1701 | C5: Fondo Resarcitorio 2026
B6: 2501 | C6: Fondo de Aportaciones para el Fortalecimiento de los Municipios 2026
B7: 2502 | C7: Fondo de Aportaciones para la Infraestructura Social Municipal 2026

Sheet COG
B2: COG | C2: CONCEPTO
B3: 21101 | C3: MATERIALES, ÚTILES Y EQUIPOS MENORES DE OFICINA
B4: 21102 | C4: BIENES MUEBLES MENORES DE OFICINA
B5: 21201 | C5: MATERIALES Y ÚTILES DE IMPRESIÓN Y REPRODUCCIÓN
B6: 21202 | C6: BIENES MUEBLES MENORES DE IMPRESIÓN Y REPRODUCCIÓN
B7: 21301 | C7: MATERIAL ESTADÍSTICO Y GEOGRÁFICO
B8: 21302 | C8: BIENES MUEBLES MENORES DE ESTADÍSTICA Y GEOGRAFÍA
B9: 21401 | C9: MATERIALES, ÚTILES Y EQUIPOS MENORES DE TECNOLOGÍAS DE LA INFORMACIÓN Y COMUNICACIONES
B10: 21402 | C10: BIENES MENORES DE TECNOLOGÍAS DE LA INFORMACIÓN Y COMUNICACIONES
B11: 21501 | C11: MATERIAL IMPRESO E INFORMACIÓN DIGITAL
B12: 21601 | C12: MATERIAL DE LIMPIEZA
B13: 21701 | C13: MATERIALES Y ÚTILES DE ENSEÑANZA
B14: 21801 | C14: MATERIALES PARA EL REGISTRO E IDENTIFICACIÓN DE BIENES Y PERSONAS
... B290: 63209 | C290: OTROS PROYECTOS PRODUCTIVOS Y ACCIONES DE FOMENTO

Sheet PROYECTO
B2: PROYECTO | C2: CONCEPTO
B3: =+TEXT(E3,"000") -> 001 | C3: MODERNIZACIÓN DE SEGURIDAD PÚBLICA | E3: 001
B4: =+TEXT(E4,"000") -> 002 | C4: ATENCIÓN Y PARTICIPACIÓN CIUDADANA | E4: 002
B5: =+TEXT(E5,"000") -> 003 | C5: Informe de gobierno | E5: 003
B6: =+TEXT(E6,"000") -> 004 | C6: Cabalgata de la Independencia | E6: 004
B7: =+TEXT(E7,"000") -> 005 | C7: Intendentes | E7: 005
B8: =+TEXT(E8,"000") -> 006 | C8: Panteones Municipales - Fosas y Gavetas | E8: 006
B9: =+TEXT(E9,"000") -> 007 | C9: Alumbrado Público | E9: 007
B10: =+TEXT(E10,"000") -> 008 | C10: COMUNICACIÓN SOCIAL Y RELACIONES PÚBLICAS | E10: 008
B11: =+TEXT(E11,"000") -> 009 | C11: MUNICIPIO INCLUYENTE Y GARANTE DE LOS DERECHOS HUMANOS | E11: 009
B12: =+TEXT(E12,"000") -> 010 | C12: CABILDO ABIERTO | E12: 010
B13: =+TEXT(E13,"000") -> 011 | C13: Fiestas Patrias | E13: 011
B14: =+TEXT(E14,"000") -> 012 | C14: SEGURIDAD JURIDICA MUNICIPAL | E14: 012
... B99: =+TEXT(E99,"000") -> 097 | C99: Terreno para Universidad Rosario Castellano | E99: 097

Sheet EJES
B2: EJES
B3: 1 | C3: RINCÓN SEGURO Y CORDIAL
B4: 2 | C4: RINCÓN RESPONSABLE Y CULTO
B5: 3 | C5: RINCÓN SANO Y FELIZ
B6: 4 | C6: RINCÓN VERDE Y SOSTENIBLE
B7: 5 | C7: RINCÓN INTELIGENTE Y CAPAZ

Sheet CONDICIONES
B2: U.A. | C2: PROYECTO | D2: EJE | F2: Recursos Fiscales 2025 | G2: Participaciones 2025 | H2: Total proyecto | I2: proyección 2026 Recursos Fiscales | J2: Participaciones | K2: FORTAMUN | L2: RESARCITORIO | M2: FISMUN | N2: NOTAS
E3: Nombre del Proyecto
A4: 067 | B4: H001 | C4: 067 | D4: 2 | E4: CONTROL DEL DESARROLLO URBANO | F4: 99504.98 | H4: =+F4+G4 -> 99504.98 | I4: 700000 | N4: 1 vehículo
